{
    "layouts": {
        "layout1Player": {
            "cardSize": 14,
            "rowSpacing": 2,
            "chat": {"left": "60%", "top": "5/6", "width": "40%", "height": "1/6"},
            "regions": {
                "sharedLocations":         {"groupId": "sharedLocations",         "type": "free","direction": "horizontal", "left":  "0%", "top":  "0%", "width": "40%", "height": "5/6"},
                "sharedEncounterDiscard":  {"groupId": "sharedEncounterDiscard",  "type": "pile","direction": "horizontal", "left": "40%", "top":  "0%", "width":  "9%", "height": "1/6"},
                "sharedEncounterDeck":     {"groupId": "sharedEncounterDeck",     "type": "pile","direction": "horizontal", "left": "49%", "top":  "0%", "width":  "9%", "height": "1/6"},
                "sharedAgendaDeck":        {"groupId": "sharedAgendaDeck",        "type": "pile","direction": "horizontal", "left": "58%", "top":  "0%", "width": "11%", "height": "1/6"},
                "sharedActDeck":           {"groupId": "sharedActDeck",           "type": "pile","direction": "horizontal", "left": "69%", "top":  "0%", "width": "11%", "height": "1/6"},
                "sharedScenarioReference": {"groupId": "sharedScenarioReference", "type": "pile","direction": "horizontal", "left": "80%", "top":  "0%", "width":  "9%", "height": "1/6"},
                "player1Investigator":     {"groupId": "player1Investigator",     "type": "row", "direction": "horizontal", "left": "40%", "top": "3/6", "width": "11%", "height": "1/6"},
                "player1Threat":           {"groupId": "player1Threat",           "type": "row", "direction": "horizontal", "left": "51%", "top": "3/6", "width": "49%", "height": "1/6"},
                "player1Play1":            {"groupId": "player1Play1",            "type": "row", "direction": "horizontal", "left": "40%", "top": "4/6", "width": "60%", "height": "1/6"},
                "playerNHand":             {"groupId": "playerNHand",             "type": "fan", "direction": "horizontal", "left":  "0%", "top": "5/6", "width": "44%", "height": "1/6", "style": {"background": "rgba(0, 0, 0, 0.3)"}, "showMenu": true},
                "playerNDeck":             {"groupId": "playerNDeck",             "type": "pile","direction": "horizontal", "left": "44%", "top": "5/6", "width":  "8%", "height": "1/6", "style": {"background": "rgba(0, 0, 0, 0.3)"}},
                "playerNDiscard":          {"groupId": "playerNDiscard",          "type": "pile","direction": "horizontal", "left": "52%", "top": "5/6", "width":  "8%", "height": "1/6", "style": {"background": "rgba(0, 0, 0, 0.3)"}},
                "sharedSetAside":          {"groupId": "sharedSetAside",          "type": "row", "direction": "horizontal", "left": 0.1, "top": "1/12","width": "80%",  "height": "1/5", "visible": false, "showMenu": true, "layerIndex": 1, "style": {"background": "rgba(55, 65, 81)", "borderRadius": "2vh", "padding": "1vh", "boxShadow": "0 0 1vh 1vh rgba(0, 0, 0, 1)"}},
                "sharedFaceupPile1":       {"groupId": "sharedFaceupPile1",       "type": "pile","direction": "horizontal", "left": 0.35,"top": "4/12","width": "10%",  "height": "1/5", "visible": false, "showMenu": true, "layerIndex": 1, "style": {"background": "rgba(55, 65, 81)", "borderRadius": "2vh", "padding": "1vh", "boxShadow": "0 0 1vh 1vh rgba(0, 0, 0, 1)"}},
                "sharedFaceupPile2":       {"groupId": "sharedFaceupPile2",       "type": "pile","direction": "horizontal", "left": 0.55,"top": "4/12","width": "10%",  "height": "1/5", "visible": false, "showMenu": true, "layerIndex": 1, "style": {"background": "rgba(55, 65, 81)", "borderRadius": "2vh", "padding": "1vh", "boxShadow": "0 0 1vh 1vh rgba(0, 0, 0, 1)"}},
                "sharedFacedownPile1":     {"groupId": "sharedFacedownPile1",     "type": "pile","direction": "horizontal", "left": 0.35,"top": "7/12","width": "10%",  "height": "1/5", "visible": false, "showMenu": true, "layerIndex": 1, "style": {"background": "rgba(55, 65, 81)", "borderRadius": "2vh", "padding": "1vh", "boxShadow": "0 0 1vh 1vh rgba(0, 0, 0, 1)"}},
                "sharedFacedownPile2":     {"groupId": "sharedFacedownPile2",     "type": "pile","direction": "horizontal", "left": 0.55,"top": "7/12","width": "10%",  "height": "1/5", "visible": false, "showMenu": true, "layerIndex": 1, "style": {"background": "rgba(55, 65, 81)", "borderRadius": "2vh", "padding": "1vh", "boxShadow": "0 0 1vh 1vh rgba(0, 0, 0, 1)"}}
            },
            "tableButtons": {
            }
        },
        "layout2Player": {
            "cardSize": 14,
            "rowSpacing": 2,
            "chat": {"left": "60%", "top": "5/6", "width": "40%", "height": "1/6"},
            "regions": {
                "sharedLocations":         {"groupId": "sharedLocations",         "type": "free","direction": "horizontal", "left":  "0%", "top":  "0%", "width": "40%", "height": "5/6"},
                "sharedEncounterDiscard":  {"groupId": "sharedEncounterDiscard",  "type": "pile","direction": "horizontal", "left": "40%", "top":  "0%", "width":  "9%", "height": "1/6"},
                "sharedEncounterDeck":     {"groupId": "sharedEncounterDeck",     "type": "pile","direction": "horizontal", "left": "49%", "top":  "0%", "width":  "9%", "height": "1/6"},
                "sharedAgendaDeck":        {"groupId": "sharedAgendaDeck",        "type": "pile","direction": "horizontal", "left": "58%", "top":  "0%", "width": "11%", "height": "1/6"},
                "sharedActDeck":           {"groupId": "sharedActDeck",           "type": "pile","direction": "horizontal", "left": "69%", "top":  "0%", "width": "11%", "height": "1/6"},
                "sharedScenarioReference": {"groupId": "sharedScenarioReference", "type": "pile","direction": "horizontal", "left": "80%", "top":  "0%", "width":  "9%", "height": "1/6"},
                "player1Investigator":     {"groupId": "player1Investigator",     "type": "row", "direction": "horizontal", "left": "40%", "top": "1/6", "width": "11%", "height": "1/6"},
                "player1Threat":           {"groupId": "player1Threat",           "type": "row", "direction": "horizontal", "left": "51%", "top": "1/6", "width": "49%", "height": "1/6"},
                "player1Play1":            {"groupId": "player1Play1",            "type": "row", "direction": "horizontal", "left": "40%", "top": "2/6", "width": "60%", "height": "1/6"},
                "player2Investigator":     {"groupId": "player2Investigator",     "type": "row", "direction": "horizontal", "left": "40%", "top": "3/6", "width": "11%", "height": "1/6"},
                "player2Threat":           {"groupId": "player2Threat",           "type": "row", "direction": "horizontal", "left": "51%", "top": "3/6", "width": "49%", "height": "1/6"},
                "player2Play1":            {"groupId": "player2Play1",            "type": "row", "direction": "horizontal", "left": "40%", "top": "4/6", "width": "60%", "height": "1/6"},
                "playerNHand":             {"groupId": "playerNHand",             "type": "fan", "direction": "horizontal", "left":  "0%", "top": "5/6", "width": "44%", "height": "1/6", "style": {"background": "rgba(0, 0, 0, 0.3)"}, "showMenu": true},
                "playerNDeck":             {"groupId": "playerNDeck",             "type": "pile","direction": "horizontal", "left": "44%", "top": "5/6", "width":  "8%", "height": "1/6", "style": {"background": "rgba(0, 0, 0, 0.3)"}},
                "playerNDiscard":          {"groupId": "playerNDiscard",          "type": "pile","direction": "horizontal", "left": "52%", "top": "5/6", "width":  "8%", "height": "1/6", "style": {"background": "rgba(0, 0, 0, 0.3)"}},
                "sharedSetAside":          {"groupId": "sharedSetAside",          "type": "row", "direction": "horizontal", "left": 0.1, "top": "1/12","width": "80%",  "height": "1/5", "visible": false, "showMenu": true, "layerIndex": 1, "style": {"background": "rgba(55, 65, 81)", "borderRadius": "2vh", "padding": "1vh", "boxShadow": "0 0 1vh 1vh rgba(0, 0, 0, 1)"}},
                "sharedFaceupPile1":       {"groupId": "sharedFaceupPile1",       "type": "pile","direction": "horizontal", "left": 0.35,"top": "4/12","width": "10%",  "height": "1/5", "visible": false, "showMenu": true, "layerIndex": 1, "style": {"background": "rgba(55, 65, 81)", "borderRadius": "2vh", "padding": "1vh", "boxShadow": "0 0 1vh 1vh rgba(0, 0, 0, 1)"}},
                "sharedFaceupPile2":       {"groupId": "sharedFaceupPile2",       "type": "pile","direction": "horizontal", "left": 0.55,"top": "4/12","width": "10%",  "height": "1/5", "visible": false, "showMenu": true, "layerIndex": 1, "style": {"background": "rgba(55, 65, 81)", "borderRadius": "2vh", "padding": "1vh", "boxShadow": "0 0 1vh 1vh rgba(0, 0, 0, 1)"}},
                "sharedFacedownPile1":     {"groupId": "sharedFacedownPile1",     "type": "pile","direction": "horizontal", "left": 0.35,"top": "7/12","width": "10%",  "height": "1/5", "visible": false, "showMenu": true, "layerIndex": 1, "style": {"background": "rgba(55, 65, 81)", "borderRadius": "2vh", "padding": "1vh", "boxShadow": "0 0 1vh 1vh rgba(0, 0, 0, 1)"}},
                "sharedFacedownPile2":     {"groupId": "sharedFacedownPile2",     "type": "pile","direction": "horizontal", "left": 0.55,"top": "7/12","width": "10%",  "height": "1/5", "visible": false, "showMenu": true, "layerIndex": 1, "style": {"background": "rgba(55, 65, 81)", "borderRadius": "2vh", "padding": "1vh", "boxShadow": "0 0 1vh 1vh rgba(0, 0, 0, 1)"}}
            },
            "tableButtons": {
            }
        },
        "layout3Player": {
            "cardSize": 14,
            "rowSpacing": 2,
            "chat": {"left": "60%", "top": "5/6", "width": "40%", "height": "1/6"},
            "regions": {
                "sharedLocations":         {"groupId": "sharedLocations",         "type": "free","direction": "horizontal", "left":  "0%", "top":  "0%", "width": "40%", "height": "5/6"},
                "sharedEncounterDiscard":  {"groupId": "sharedEncounterDiscard",  "type": "pile","direction": "horizontal", "left": "40%", "top":  "0%", "width":  "9%", "height": "1/6"},
                "sharedEncounterDeck":     {"groupId": "sharedEncounterDeck",     "type": "pile","direction": "horizontal", "left": "49%", "top":  "0%", "width":  "9%", "height": "1/6"},
                "sharedAgendaDeck":        {"groupId": "sharedAgendaDeck",        "type": "pile","direction": "horizontal", "left": "58%", "top":  "0%", "width": "11%", "height": "1/6"},
                "sharedActDeck":           {"groupId": "sharedActDeck",           "type": "pile","direction": "horizontal", "left": "69%", "top":  "0%", "width": "11%", "height": "1/6"},
                "sharedScenarioReference": {"groupId": "sharedScenarioReference", "type": "pile","direction": "horizontal", "left": "80%", "top":  "0%", "width":  "9%", "height": "1/6"},
                "player1Threat":           {"groupId": "player1Threat",           "type": "row", "direction": "horizontal", "left": "40%", "top": "2/6", "width": "18%", "height": "1/6"},
                "player1Investigator":     {"groupId": "player1Investigator",     "type": "row", "direction": "horizontal", "left": "58%", "top": "2/6", "width": "11%", "height": "1/6"},
                "player1Play1":            {"groupId": "player1Play1",            "type": "row", "direction": "horizontal", "left": "69%", "top": "2/6", "width": "31%", "height": "1/6"},
                "player2Threat":           {"groupId": "player2Threat",           "type": "row", "direction": "horizontal", "left": "40%", "top": "3/6", "width": "18%", "height": "1/6"},
                "player2Investigator":     {"groupId": "player2Investigator",     "type": "row", "direction": "horizontal", "left": "58%", "top": "3/6", "width": "11%", "height": "1/6"},
                "player2Play1":            {"groupId": "player2Play1",            "type": "row", "direction": "horizontal", "left": "69%", "top": "3/6", "width": "31%", "height": "1/6"},
                "player3Threat":           {"groupId": "player3Threat",           "type": "row", "direction": "horizontal", "left": "40%", "top": "4/6", "width": "18%", "height": "1/6"},
                "player3Investigator":     {"groupId": "player3Investigator",     "type": "row", "direction": "horizontal", "left": "58%", "top": "4/6", "width": "11%", "height": "1/6"},
                "player3Play1":            {"groupId": "player3Play1",            "type": "row", "direction": "horizontal", "left": "69%", "top": "4/6", "width": "31%", "height": "1/6"},
                "playerNHand":             {"groupId": "playerNHand",             "type": "fan", "direction": "horizontal", "left":  "0%", "top": "5/6", "width": "44%", "height": "1/6", "style": {"background": "rgba(0, 0, 0, 0.3)"}, "showMenu": true},
                "playerNDeck":             {"groupId": "playerNDeck",             "type": "pile","direction": "horizontal", "left": "44%", "top": "5/6", "width":  "8%", "height": "1/6", "style": {"background": "rgba(0, 0, 0, 0.3)"}},
                "playerNDiscard":          {"groupId": "playerNDiscard",          "type": "pile","direction": "horizontal", "left": "52%", "top": "5/6", "width":  "8%", "height": "1/6", "style": {"background": "rgba(0, 0, 0, 0.3)"}},
                "sharedSetAside":          {"groupId": "sharedSetAside",          "type": "row", "direction": "horizontal", "left": 0.1, "top": "1/12","width": "80%",  "height": "1/5", "visible": false, "showMenu": true, "layerIndex": 1, "style": {"background": "rgba(55, 65, 81)", "borderRadius": "2vh", "padding": "1vh", "boxShadow": "0 0 1vh 1vh rgba(0, 0, 0, 1)"}},
                "sharedFaceupPile1":       {"groupId": "sharedFaceupPile1",       "type": "pile","direction": "horizontal", "left": 0.35,"top": "4/12","width": "10%",  "height": "1/5", "visible": false, "showMenu": true, "layerIndex": 1, "style": {"background": "rgba(55, 65, 81)", "borderRadius": "2vh", "padding": "1vh", "boxShadow": "0 0 1vh 1vh rgba(0, 0, 0, 1)"}},
                "sharedFaceupPile2":       {"groupId": "sharedFaceupPile2",       "type": "pile","direction": "horizontal", "left": 0.55,"top": "4/12","width": "10%",  "height": "1/5", "visible": false, "showMenu": true, "layerIndex": 1, "style": {"background": "rgba(55, 65, 81)", "borderRadius": "2vh", "padding": "1vh", "boxShadow": "0 0 1vh 1vh rgba(0, 0, 0, 1)"}},
                "sharedFacedownPile1":     {"groupId": "sharedFacedownPile1",     "type": "pile","direction": "horizontal", "left": 0.35,"top": "7/12","width": "10%",  "height": "1/5", "visible": false, "showMenu": true, "layerIndex": 1, "style": {"background": "rgba(55, 65, 81)", "borderRadius": "2vh", "padding": "1vh", "boxShadow": "0 0 1vh 1vh rgba(0, 0, 0, 1)"}},
                "sharedFacedownPile2":     {"groupId": "sharedFacedownPile2",     "type": "pile","direction": "horizontal", "left": 0.55,"top": "7/12","width": "10%",  "height": "1/5", "visible": false, "showMenu": true, "layerIndex": 1, "style": {"background": "rgba(55, 65, 81)", "borderRadius": "2vh", "padding": "1vh", "boxShadow": "0 0 1vh 1vh rgba(0, 0, 0, 1)"}}
            },
            "tableButtons": {
            }
        },
        "layout4Player": {
            "cardSize": 14,
            "rowSpacing": 2,
            "chat": {"left": "60%", "top": "5/6", "width": "40%", "height": "1/6"},
            "regions": {
                "sharedLocations":         {"groupId": "sharedLocations",         "type": "free","direction": "horizontal", "left":  "0%", "top":  "0%", "width": "40%", "height": "5/6"},
                "sharedEncounterDiscard":  {"groupId": "sharedEncounterDiscard",  "type": "pile","direction": "horizontal", "left": "40%", "top":  "0%", "width":  "9%", "height": "1/6"},
                "sharedEncounterDeck":     {"groupId": "sharedEncounterDeck",     "type": "pile","direction": "horizontal", "left": "49%", "top":  "0%", "width":  "9%", "height": "1/6"},
                "sharedAgendaDeck":        {"groupId": "sharedAgendaDeck",        "type": "pile","direction": "horizontal", "left": "58%", "top":  "0%", "width": "11%", "height": "1/6"},
                "sharedActDeck":           {"groupId": "sharedActDeck",           "type": "pile","direction": "horizontal", "left": "69%", "top":  "0%", "width": "11%", "height": "1/6"},
                "sharedScenarioReference": {"groupId": "sharedScenarioReference", "type": "pile","direction": "horizontal", "left": "80%", "top":  "0%", "width":  "9%", "height": "1/6"},
                "player1Threat":           {"groupId": "player1Threat",           "type": "row", "direction": "horizontal", "left": "40%", "top": "1/6", "width": "18%", "height": "1/6"},
                "player1Investigator":     {"groupId": "player1Investigator",     "type": "row", "direction": "horizontal", "left": "58%", "top": "1/6", "width": "11%", "height": "1/6"},
                "player1Play1":            {"groupId": "player1Play1",            "type": "row", "direction": "horizontal", "left": "69%", "top": "1/6", "width": "31%", "height": "1/6"},
                "player2Threat":           {"groupId": "player2Threat",           "type": "row", "direction": "horizontal", "left": "40%", "top": "2/6", "width": "18%", "height": "1/6"},
                "player2Investigator":     {"groupId": "player2Investigator",     "type": "row", "direction": "horizontal", "left": "58%", "top": "2/6", "width": "11%", "height": "1/6"},
                "player2Play1":            {"groupId": "player2Play1",            "type": "row", "direction": "horizontal", "left": "69%", "top": "2/6", "width": "31%", "height": "1/6"},
                "player3Threat":           {"groupId": "player3Threat",           "type": "row", "direction": "horizontal", "left": "40%", "top": "3/6", "width": "18%", "height": "1/6"},
                "player3Investigator":     {"groupId": "player3Investigator",     "type": "row", "direction": "horizontal", "left": "58%", "top": "3/6", "width": "11%", "height": "1/6"},
                "player3Play1":            {"groupId": "player3Play1",            "type": "row", "direction": "horizontal", "left": "69%", "top": "3/6", "width": "31%", "height": "1/6"},
                "player4Threat":           {"groupId": "player4Threat",           "type": "row", "direction": "horizontal", "left": "40%", "top": "4/6", "width": "18%", "height": "1/6"},
                "player4Investigator":     {"groupId": "player4Investigator",     "type": "row", "direction": "horizontal", "left": "58%", "top": "4/6", "width": "11%", "height": "1/6"},
                "player4Play1":            {"groupId": "player4Play1",            "type": "row", "direction": "horizontal", "left": "69%", "top": "4/6", "width": "31%", "height": "1/6"},
                "playerNHand":             {"groupId": "playerNHand",             "type": "fan", "direction": "horizontal", "left":  "0%", "top": "5/6", "width": "44%", "height": "1/6", "style": {"background": "rgba(0, 0, 0, 0.3)"}, "showMenu": true},
                "playerNDeck":             {"groupId": "playerNDeck",             "type": "pile","direction": "horizontal", "left": "44%", "top": "5/6", "width":  "8%", "height": "1/6", "style": {"background": "rgba(0, 0, 0, 0.3)"}},
                "playerNDiscard":          {"groupId": "playerNDiscard",          "type": "pile","direction": "horizontal", "left": "52%", "top": "5/6", "width":  "8%", "height": "1/6", "style": {"background": "rgba(0, 0, 0, 0.3)"}},
                "sharedSetAside":          {"groupId": "sharedSetAside",          "type": "row", "direction": "horizontal", "left": 0.1, "top": "1/12","width": "80%",  "height": "1/5", "visible": false, "showMenu": true, "layerIndex": 1, "style": {"background": "rgba(55, 65, 81)", "borderRadius": "2vh", "padding": "1vh", "boxShadow": "0 0 1vh 1vh rgba(0, 0, 0, 1)"}},
                "sharedFaceupPile1":       {"groupId": "sharedFaceupPile1",       "type": "pile","direction": "horizontal", "left": 0.35,"top": "4/12","width": "10%",  "height": "1/5", "visible": false, "showMenu": true, "layerIndex": 1, "style": {"background": "rgba(55, 65, 81)", "borderRadius": "2vh", "padding": "1vh", "boxShadow": "0 0 1vh 1vh rgba(0, 0, 0, 1)"}},
                "sharedFaceupPile2":       {"groupId": "sharedFaceupPile2",       "type": "pile","direction": "horizontal", "left": 0.55,"top": "4/12","width": "10%",  "height": "1/5", "visible": false, "showMenu": true, "layerIndex": 1, "style": {"background": "rgba(55, 65, 81)", "borderRadius": "2vh", "padding": "1vh", "boxShadow": "0 0 1vh 1vh rgba(0, 0, 0, 1)"}},
                "sharedFacedownPile1":     {"groupId": "sharedFacedownPile1",     "type": "pile","direction": "horizontal", "left": 0.35,"top": "7/12","width": "10%",  "height": "1/5", "visible": false, "showMenu": true, "layerIndex": 1, "style": {"background": "rgba(55, 65, 81)", "borderRadius": "2vh", "padding": "1vh", "boxShadow": "0 0 1vh 1vh rgba(0, 0, 0, 1)"}},
                "sharedFacedownPile2":     {"groupId": "sharedFacedownPile2",     "type": "pile","direction": "horizontal", "left": 0.55,"top": "7/12","width": "10%",  "height": "1/5", "visible": false, "showMenu": true, "layerIndex": 1, "style": {"background": "rgba(55, 65, 81)", "borderRadius": "2vh", "padding": "1vh", "boxShadow": "0 0 1vh 1vh rgba(0, 0, 0, 1)"}}
            },
            "tableButtons": {
            }
        }        
    }
}